storycode/__init__.py
storycode/__main__.py
storycode/pyrustic_data/backstage/config/build.json
storycode/pyrustic_data/backstage/config/init.json
storycode/pyrustic_data/backstage/config/release.json
storycode/pyrustic_data/backstage/data/github_release_form.json
storycode/pyrustic_data/backstage/report/build_report.json
storycode/pyrustic_data/backstage/report/release_report.json
storycode/pyrustic_data/hubstore/img.json
storycode/pyrustic_data/hubstore/promotion.json
tests/__init__.py
storycode-0.0.1.dist-info/LICENSE
storycode-0.0.1.dist-info/METADATA
storycode-0.0.1.dist-info/WHEEL
storycode-0.0.1.dist-info/entry_points.txt
storycode-0.0.1.dist-info/top_level.txt
storycode-0.0.1.dist-info/RECORD
