Metadata-Version: 2.1
Name: storycode
Version: 0.0.1
Summary: Cool Python app built with Pyrustic
Home-page: https://github.com/pyrustic/pyrustic
Author: Johnny Silverhand
Author-email: sapiens@earth.invalid
Maintainer: Johnny Silverhand
Maintainer-email: sapiens@earth.invalid
License: MIT
Keywords: desktop-application
Platform: UNKNOWN
Classifier: Programming Language :: Python :: 3
Classifier: License :: OSI Approved :: MIT License
Classifier: Operating System :: OS Independent
Requires-Python: >=3.5
Requires-Dist: pyrustic
